testingcgsdk/__init__.py
testingcgsdk/app.py
testingcgsdk/cglense.py
testingcgsdk-0.0.25.dist-info/METADATA
testingcgsdk-0.0.25.dist-info/WHEEL
testingcgsdk-0.0.25.dist-info/top_level.txt
testingcgsdk-0.0.25.dist-info/RECORD
