Metadata-Version: 2.1
Name: testingcgsdk
Version: 0.0.25
Requires-Dist: setuptools ==68.2.2
Requires-Dist: wheel ==0.41.2
Requires-Dist: pandas >2.0.0
Requires-Dist: numpy >1.24.0
Requires-Dist: SQLAlchemy >2.0.0
Requires-Dist: pydantic-settings >2.0.0
Requires-Dist: rich >13.0.0
Requires-Dist: psycopg2 >2.9
Requires-Dist: sqladmin >0.15.1
Requires-Dist: fastapi ==0.104.1
Requires-Dist: uvicorn ==0.24.0.post1
